pygrate
