Metadata-Version: 1.1
Name: pygrate
Version: 0.0.3
Summary: Migration tools for python
Home-page: https://git.fenrys.io/fenrys/back/python_ddd
Author: Laurent Evrard
Author-email: evrardlaurent77@gmail.com
License: WTFPL
Platform: UNKNOWN
Classifier: Programming Language :: Python
Classifier: Development Status :: 1 - Planning
Classifier: License :: OSI Approved
Classifier: Natural Language :: French
Classifier: Operating System :: OS Independent
Classifier: Programming Language :: Python :: 3.6
Classifier: Topic :: Communications
